django_master_pay/__init__.py
django_master_pay/api.py
django_master_pay/apps.py
django_master_pay/collections.py
django_master_pay/settings.py
django_master_pay/utils.py
django_master_pay/admin/__init__.py
django_master_pay/admin/payment.py
django_master_pay/management/__init__.py
django_master_pay/management/commands/__init__.py
django_master_pay/management/commands/master_pay_handler.py
django_master_pay/migrations/0001_initial.py
django_master_pay/migrations/0002_auto_20210721_1229.py
django_master_pay/migrations/0003_auto_20210726_1322.py
django_master_pay/migrations/0004_auto_20210726_1323.py
django_master_pay/migrations/0005_auto_20230927_1102.py
django_master_pay/migrations/__init__.py
django_master_pay/models/__init__.py
django_master_pay/models/payment.py
django_master_pay-1.0.7.dist-info/METADATA
django_master_pay-1.0.7.dist-info/WHEEL
django_master_pay-1.0.7.dist-info/top_level.txt
django_master_pay-1.0.7.dist-info/RECORD
