Metadata-Version: 2.1
Name: django-master-pay
Version: 1.0.7
Summary: MasterPay
Home-page: https://github.com/KokocGroup/django_master_pay
Author: KokocGroup
Author-email: dev@kokoc.com
License: BSD
Download-URL: https://github.com/KokocGroup/django_master_pay/tarball/v1.0.7
Platform: UNKNOWN
Classifier: Development Status :: 5 - Production/Stable
Classifier: Environment :: Web Environment
Classifier: Framework :: Django
Classifier: Operating System :: OS Independent
Classifier: Programming Language :: Python
Classifier: Programming Language :: Python :: 3
Classifier: Topic :: Internet :: WWW/HTTP
Requires-Dist: requests
